datazone/__init__.py
datazone/cli/__init__.py
datazone/cli/app/__init__.py
datazone/cli/app/list.py
datazone/cli/app/main.py
datazone/cli/auth/__init__.py
datazone/cli/auth/main.py
datazone/cli/dataset/__init__.py
datazone/cli/dataset/list.py
datazone/cli/dataset/main.py
datazone/cli/dataset/show.py
datazone/cli/dataset/transaction/__init__.py
datazone/cli/dataset/transaction/create.py
datazone/cli/dataset/transaction/delete.py
datazone/cli/dataset/transaction/list.py
datazone/cli/dataset/transaction/main.py
datazone/cli/dataset/transactions.py
datazone/cli/datazone_typer.py
datazone/cli/endpoint/__init__.py
datazone/cli/endpoint/create.py
datazone/cli/endpoint/delete.py
datazone/cli/endpoint/list.py
datazone/cli/endpoint/main.py
datazone/cli/execution/__init__.py
datazone/cli/execution/list.py
datazone/cli/execution/log.py
datazone/cli/execution/main.py
datazone/cli/execution/run.py
datazone/cli/extract/__init__.py
datazone/cli/extract/create.py
datazone/cli/extract/create_prompts.py
datazone/cli/extract/delete.py
datazone/cli/extract/execute.py
datazone/cli/extract/list.py
datazone/cli/extract/main.py
datazone/cli/main.py
datazone/cli/pipeline/__init__.py
datazone/cli/pipeline/create.py
datazone/cli/pipeline/delete.py
datazone/cli/pipeline/list.py
datazone/cli/pipeline/main.py
datazone/cli/profile/__init__.py
datazone/cli/profile/create.py
datazone/cli/profile/delete.py
datazone/cli/profile/list.py
datazone/cli/profile/main.py
datazone/cli/profile/set_default.py
datazone/cli/project/__init__.py
datazone/cli/project/activities.py
datazone/cli/project/clone.py
datazone/cli/project/create.py
datazone/cli/project/deploy.py
datazone/cli/project/list.py
datazone/cli/project/main.py
datazone/cli/project/pull.py
datazone/cli/project/summary.py
datazone/cli/run/main.py
datazone/cli/schedule/__init__.py
datazone/cli/schedule/create.py
datazone/cli/schedule/delete.py
datazone/cli/schedule/list.py
datazone/cli/schedule/main.py
datazone/cli/source/__init__.py
datazone-0.0.18.dist-info/METADATA
datazone-0.0.18.dist-info/WHEEL
datazone-0.0.18.dist-info/entry_points.txt
datazone-0.0.18.dist-info/RECORD
