Metadata-Version: 2.4
Name: datazone
Version: 0.0.18
Summary: Datazone Client Package
Author: resulyurttakalan
Author-email: resul@datazone.co
Requires-Python: >=3.9,<4.0
Classifier: Programming Language :: Python :: 3
Classifier: Programming Language :: Python :: 3.9
Classifier: Programming Language :: Python :: 3.10
Classifier: Programming Language :: Python :: 3.11
Classifier: Programming Language :: Python :: 3.12
Classifier: Programming Language :: Python :: 3.13
Classifier: Programming Language :: Python :: 3.14
Provides-Extra: pyspark
Requires-Dist: bson (>=0.5,<0.6)
Requires-Dist: click (==8.1.3)
Requires-Dist: deltalake (>=0.25.5,<0.26.0)
Requires-Dist: fernet (>=1.0.1,<2.0.0)
Requires-Dist: gitpython (>=3.1.31,<4.0.0)
Requires-Dist: jinja2 (>=3.1.2,<4.0.0)
Requires-Dist: loguru (>=0.7.2,<0.8.0)
Requires-Dist: numpy (==1.26.4)
Requires-Dist: oauthlib (>=3.2.2,<4.0.0)
Requires-Dist: pydantic (>=2.0,<3.0)
Requires-Dist: pyspark (>=3.3.2,<4.0.0) ; extra == "pyspark"
Requires-Dist: pyyaml (>=6.0,<7.0)
Requires-Dist: questionary (>=2.0.1,<3.0.0)
Requires-Dist: requests (>=2.32.3,<3.0.0)
Requires-Dist: toml (>=0.10.2,<0.11.0)
Requires-Dist: typer[all] (>=0.7.0,<0.8.0)
